stop_watch/__init__.py
stop_watch/main.py
simple_stop_watch_utility-2.0.1.dist-info/LICENSE
simple_stop_watch_utility-2.0.1.dist-info/METADATA
simple_stop_watch_utility-2.0.1.dist-info/WHEEL
simple_stop_watch_utility-2.0.1.dist-info/top_level.txt
simple_stop_watch_utility-2.0.1.dist-info/RECORD
